website_checker/__init__.py
website_checker/checks.py
website_checker/cli.py
website_checker/helpers.py
website_checker-0.3.3.dist-info/entry_points.txt
website_checker-0.3.3.dist-info/LICENSE
website_checker-0.3.3.dist-info/WHEEL
website_checker-0.3.3.dist-info/METADATA
website_checker-0.3.3.dist-info/RECORD
