Metadata-Version: 2.1
Name: website-checker
Version: 0.3.3
Summary: A simple python application for running checks against websites.
Home-page: https://aidanmelen.github.io/website-checker
License: MIT
Keywords: website,checker
Author: Aidan Melen
Author-email: aidanmelen@protonmail.com
Requires-Python: >=3.8,<4.0
Classifier: License :: OSI Approved :: MIT License
Classifier: Programming Language :: Python :: 3
Classifier: Programming Language :: Python :: 3.8
Classifier: Programming Language :: Python :: 3.9
Requires-Dist: click (>=7.1.2,<8.0.0)
Requires-Dist: requests (>=2.25.0,<3.0.0)
Requires-Dist: structlog (>=20.1.0,<21.0.0)
Project-URL: Repository, https://github.com/aidanmelen/website-checker
